<?xml version="1.0" encoding="utf-8"?><toc><breadcrumbs><li><a href="N_MoreLinq.htm">Docs</a></li><li><a href="N_MoreLinq_Experimental.htm">More<wbr />Linq.<wbr />Experimental</a></li><li><a href="T_MoreLinq_Experimental_ExperimentalEnumerable.htm">Experimental<wbr />Enumerable</a></li><li><a href="Methods_T_MoreLinq_Experimental_ExperimentalEnumerable.htm">Methods</a></li><li><a href="Overload_MoreLinq_Experimental_ExperimentalEnumerable_Aggregate.htm">Aggregate</a></li></breadcrumbs><tocItems><li><a id="M_MoreLinq_Experimental_ExperimentalEnumerable_Aggregate__4" href="M_MoreLinq_Experimental_ExperimentalEnumerable_Aggregate__4.htm">Aggregate&lt;T, TResult<wbr />1, TResult<wbr />2, TResult&gt;(<wbr />IEnumerable&lt;T&gt;, Func&lt;IObservable&lt;T&gt;, IObservable&lt;TResult<wbr />1&gt;&gt;, Func&lt;IObservable&lt;T&gt;, IObservable&lt;TResult<wbr />2&gt;&gt;, Func&lt;TResult<wbr />1, TResult<wbr />2, TResult&gt;)</a></li><li><a id="M_MoreLinq_Experimental_ExperimentalEnumerable_Aggregate__5" href="M_MoreLinq_Experimental_ExperimentalEnumerable_Aggregate__5.htm">Aggregate&lt;T, TResult<wbr />1, TResult<wbr />2, TResult<wbr />3, TResult&gt;(<wbr />IEnumerable&lt;T&gt;, Func&lt;IObservable&lt;T&gt;, IObservable&lt;TResult<wbr />1&gt;&gt;, Func&lt;IObservable&lt;T&gt;, IObservable&lt;TResult<wbr />2&gt;&gt;, Func&lt;IObservable&lt;T&gt;, IObservable&lt;TResult<wbr />3&gt;&gt;, Func&lt;TResult<wbr />1, TResult<wbr />2, TResult<wbr />3, TResult&gt;)</a></li><li><a id="M_MoreLinq_Experimental_ExperimentalEnumerable_Aggregate__6" href="M_MoreLinq_Experimental_ExperimentalEnumerable_Aggregate__6.htm">Aggregate&lt;T, TResult<wbr />1, TResult<wbr />2, TResult<wbr />3, TResult<wbr />4, TResult&gt;(<wbr />IEnumerable&lt;T&gt;, Func&lt;IObservable&lt;T&gt;, IObservable&lt;TResult<wbr />1&gt;&gt;, Func&lt;IObservable&lt;T&gt;, IObservable&lt;TResult<wbr />2&gt;&gt;, Func&lt;IObservable&lt;T&gt;, IObservable&lt;TResult<wbr />3&gt;&gt;, Func&lt;IObservable&lt;T&gt;, IObservable&lt;TResult<wbr />4&gt;&gt;, Func&lt;TResult<wbr />1, TResult<wbr />2, TResult<wbr />3, TResult<wbr />4, TResult&gt;)</a></li><li><a id="M_MoreLinq_Experimental_ExperimentalEnumerable_Aggregate__7" href="M_MoreLinq_Experimental_ExperimentalEnumerable_Aggregate__7.htm">Aggregate&lt;T, TResult<wbr />1, TResult<wbr />2, TResult<wbr />3, TResult<wbr />4, TResult<wbr />5, TResult&gt;(<wbr />IEnumerable&lt;T&gt;, Func&lt;IObservable&lt;T&gt;, IObservable&lt;TResult<wbr />1&gt;&gt;, Func&lt;IObservable&lt;T&gt;, IObservable&lt;TResult<wbr />2&gt;&gt;, Func&lt;IObservable&lt;T&gt;, IObservable&lt;TResult<wbr />3&gt;&gt;, Func&lt;IObservable&lt;T&gt;, IObservable&lt;TResult<wbr />4&gt;&gt;, Func&lt;IObservable&lt;T&gt;, IObservable&lt;TResult<wbr />5&gt;&gt;, Func&lt;TResult<wbr />1, TResult<wbr />2, TResult<wbr />3, TResult<wbr />4, TResult<wbr />5, TResult&gt;)</a></li><li><a id="M_MoreLinq_Experimental_ExperimentalEnumerable_Aggregate__8" href="M_MoreLinq_Experimental_ExperimentalEnumerable_Aggregate__8.htm">Aggregate&lt;T, TResult<wbr />1, TResult<wbr />2, TResult<wbr />3, TResult<wbr />4, TResult<wbr />5, TResult<wbr />6, TResult&gt;(<wbr />IEnumerable&lt;T&gt;, Func&lt;IObservable&lt;T&gt;, IObservable&lt;TResult<wbr />1&gt;&gt;, Func&lt;IObservable&lt;T&gt;, IObservable&lt;TResult<wbr />2&gt;&gt;, Func&lt;IObservable&lt;T&gt;, IObservable&lt;TResult<wbr />3&gt;&gt;, Func&lt;IObservable&lt;T&gt;, IObservable&lt;TResult<wbr />4&gt;&gt;, Func&lt;IObservable&lt;T&gt;, IObservable&lt;TResult<wbr />5&gt;&gt;, Func&lt;IObservable&lt;T&gt;, IObservable&lt;TResult<wbr />6&gt;&gt;, Func&lt;TResult<wbr />1, TResult<wbr />2, TResult<wbr />3, TResult<wbr />4, TResult<wbr />5, TResult<wbr />6, TResult&gt;)</a></li><li><a id="M_MoreLinq_Experimental_ExperimentalEnumerable_Aggregate__9" href="M_MoreLinq_Experimental_ExperimentalEnumerable_Aggregate__9.htm">Aggregate&lt;T, TResult<wbr />1, TResult<wbr />2, TResult<wbr />3, TResult<wbr />4, TResult<wbr />5, TResult<wbr />6, TResult<wbr />7, TResult&gt;(<wbr />IEnumerable&lt;T&gt;, Func&lt;IObservable&lt;T&gt;, IObservable&lt;TResult<wbr />1&gt;&gt;, Func&lt;IObservable&lt;T&gt;, IObservable&lt;TResult<wbr />2&gt;&gt;, Func&lt;IObservable&lt;T&gt;, IObservable&lt;TResult<wbr />3&gt;&gt;, Func&lt;IObservable&lt;T&gt;, IObservable&lt;TResult<wbr />4&gt;&gt;, Func&lt;IObservable&lt;T&gt;, IObservable&lt;TResult<wbr />5&gt;&gt;, Func&lt;IObservable&lt;T&gt;, IObservable&lt;TResult<wbr />6&gt;&gt;, Func&lt;IObservable&lt;T&gt;, IObservable&lt;TResult<wbr />7&gt;&gt;, Func&lt;TResult<wbr />1, TResult<wbr />2, TResult<wbr />3, TResult<wbr />4, TResult<wbr />5, TResult<wbr />6, TResult<wbr />7, TResult&gt;)</a></li><li><a id="M_MoreLinq_Experimental_ExperimentalEnumerable_Aggregate__10" href="M_MoreLinq_Experimental_ExperimentalEnumerable_Aggregate__10.htm">Aggregate&lt;T, TResult<wbr />1, TResult<wbr />2, TResult<wbr />3, TResult<wbr />4, TResult<wbr />5, TResult<wbr />6, TResult<wbr />7, TResult<wbr />8, TResult&gt;(<wbr />IEnumerable&lt;T&gt;, Func&lt;IObservable&lt;T&gt;, IObservable&lt;TResult<wbr />1&gt;&gt;, Func&lt;IObservable&lt;T&gt;, IObservable&lt;TResult<wbr />2&gt;&gt;, Func&lt;IObservable&lt;T&gt;, IObservable&lt;TResult<wbr />3&gt;&gt;, Func&lt;IObservable&lt;T&gt;, IObservable&lt;TResult<wbr />4&gt;&gt;, Func&lt;IObservable&lt;T&gt;, IObservable&lt;TResult<wbr />5&gt;&gt;, Func&lt;IObservable&lt;T&gt;, IObservable&lt;TResult<wbr />6&gt;&gt;, Func&lt;IObservable&lt;T&gt;, IObservable&lt;TResult<wbr />7&gt;&gt;, Func&lt;IObservable&lt;T&gt;, IObservable&lt;TResult<wbr />8&gt;&gt;, Func&lt;TResult<wbr />1, TResult<wbr />2, TResult<wbr />3, TResult<wbr />4, TResult<wbr />5, TResult<wbr />6, TResult<wbr />7, TResult<wbr />8, TResult&gt;)</a></li></tocItems></toc>